{
  "day_folder": "pix (3)",
  "date_info": "26 set. 2025",
  "header_text": "26 set. 2025",
  "transactions": [
    {
      "quadrant_number": 2,
      "raw_text": "Pix R$ 27,50\n& 19:53 e ROSEVALDO FREIRE Processando taxa >",
      "processed_text": "Pix R$ 27,50 19:53 e ROSEVALDO FREIRE Processando taxa",
      "confidence": 74.0,
      "timestamp": null,
      "amount": "R$ 27,50",
      "description": "Pix R$ 27,50 19:53 e ROSEVALDO FREIRE Processando taxa"
    },
    {
      "quadrant_number": 3,
      "raw_text": "Pix R$ 15,50\n& 10:18 « Rodrigo Santos de Processando taxa >",
      "processed_text": "Pix R$ 15,50 10:18 Rodrigo Santos de Processando taxa",
      "confidence": 70.08333333333333,
      "timestamp": null,
      "amount": "R$ 15,50",
      "description": "Pix R$ 15,50 10:18 Rodrigo Santos de Processando taxa"
    },
    {
      "quadrant_number": 4,
      "raw_text": "Dix R$ 12,00\nQ& 18:48 MARIAVALDIZIADE —-Processando taxa >",
      "processed_text": "Dix R$ 12,00 Q 18:48 MARIAVALDIZIADE -Processando taxa",
      "confidence": 49.0,
      "timestamp": null,
      "amount": "R$ 12,00",
      "description": "Dix R$ 12,00 Q 18:48 MARIAVALDIZIADE -Processando taxa"
    },
    {
      "quadrant_number": 5,
      "raw_text": "Pix R$ 3,00\n& 18:12 « GABRIEL DIAS DOS Processando'taxa: >\nSANTOS MELO",
      "processed_text": "Pix R$ 3,00 18:12 GABRIEL DIAS DOS Processando taxa: SANTOS MELO",
      "confidence": 79.76923076923077,
      "timestamp": null,
      "amount": "R$ 3,00",
      "description": "Pix R$ 3,00 18:12 GABRIEL DIAS DOS Processando taxa: SANTOS MELO"
    },
    {
      "quadrant_number": 6,
      "raw_text": "Pix R$ 14,00\n& 18:10 © PEDRO JAMIRSILVERIO Processando taxa >",
      "processed_text": "Pix R$ 14,00 18:10 PEDRO JAMIRSILVERIO Processando taxa",
      "confidence": 65.72727272727273,
      "timestamp": null,
      "amount": "R$ 14,00",
      "description": "Pix R$ 14,00 18:10 PEDRO JAMIRSILVERIO Processando taxa"
    },
    {
      "quadrant_number": 7,
      "raw_text": "Pix R$ 10,00\n& 17:59 » Mayra Kelly da Silva Processando taxa >",
      "processed_text": "Pix R$ 10,00 17:59 Mayra Kelly da Silva Processando taxa",
      "confidence": 80.84615384615384,
      "timestamp": null,
      "amount": "R$ 10,00",
      "description": "Pix R$ 10,00 17:59 Mayra Kelly da Silva Processando taxa"
    },
    {
      "quadrant_number": 8,
      "raw_text": "Pix R$ 9,50\n& 17:51 * MARIZA GONCALVES Processando taxa >",
      "processed_text": "Pix R$ 9,50 17:51 MARIZA GONCALVES Processando taxa",
      "confidence": 76.63636363636364,
      "timestamp": null,
      "amount": "R$ 9,50",
      "description": "Pix R$ 9,50 17:51 MARIZA GONCALVES Processando taxa"
    },
    {
      "quadrant_number": 9,
      "raw_text": "Pix R$ 4,00\nQ 17:41 + MARLENEBRAGADO —_—~Processandotaxa >\nNASCIMENTO [ Aprovada |",
      "processed_text": "Pix R$ 4,00 Q 17:41 + MARLENEBRAGADO _ Processandotaxa NASCIMENTO Aprovada",
      "confidence": 69.36363636363636,
      "timestamp": null,
      "amount": "R$ 4,00",
      "description": "Pix R$ 4,00 Q 17:41 + MARLENEBRAGADO _ Processandotaxa NASCIMENTO Aprovada"
    },
    {
      "quadrant_number": 10,
      "raw_text": "R$ 18,00\ng, Pix Processando taxa\nyp ; ; _ >\n16:49 e Taynah Santos Benicio :\nAprovada |",
      "processed_text": "R$ 18,00 g, Pix Processando taxa yp _ 16:49 e Taynah Santos Benicio : Aprovada",
      "confidence": 73.94736842105263,
      "timestamp": null,
      "amount": "R$ 18,00",
      "description": "R$ 18,00 g, Pix Processando taxa yp _ 16:49 e Taynah Santos Benicio : Aprovada"
    },
    {
      "quadrant_number": 11,
      "raw_text": "R$ 13,00\ng, Pix Processando taxa «\na ro >\n16:33 » Andressa da Silva Costa\nAprovada |",
      "processed_text": "R$ 13,00 g, Pix Processando taxa a ro 16:33 Andressa da Silva Costa Aprovada",
      "confidence": 76.11764705882354,
      "timestamp": null,
      "amount": "R$ 13,00",
      "description": "R$ 13,00 g, Pix Processando taxa a ro 16:33 Andressa da Silva Costa Aprovada"
    },
    {
      "quadrant_number": 12,
      "raw_text": "; R$ 17,30\n& Pix Processando taxa »\nS\n16:08 e NALU ANDRADE MOTA |\nAprovada |",
      "processed_text": "R$ 17,30 Pix Processando taxa S 16:08 e NALU ANDRADE MOTA Aprovada",
      "confidence": 72.76470588235294,
      "timestamp": null,
      "amount": "R$ 17,30",
      "description": "R$ 17,30 Pix Processando taxa S 16:08 e NALU ANDRADE MOTA Aprovada"
    }
  ],
  "total_quadrants": 12,
  "processing_timestamp": "2025-10-10T11:09:50.498197"
}